chemgraphbuilder/__init__.py
chemgraphbuilder/add_graph_nodes.py
chemgraphbuilder/add_graph_relationships.py
chemgraphbuilder/graph_nodes_loader.py
chemgraphbuilder/graph_relationships_loader.py
chemgraphbuilder/neo4jdriver.py
chemgraphbuilder/node_collector_processor.py
chemgraphbuilder/node_data_processor.py
chemgraphbuilder/node_properties_extractor.py
chemgraphbuilder/relationship_collector_processor.py
chemgraphbuilder/relationship_data_processor.py
chemgraphbuilder/relationship_properties_extractor.py
chemgraphbuilder/setup_data_folder.py
chemgraphbuilder-1.18.3.dist-info/METADATA
chemgraphbuilder-1.18.3.dist-info/WHEEL
chemgraphbuilder-1.18.3.dist-info/entry_points.txt
chemgraphbuilder-1.18.3.dist-info/top_level.txt
chemgraphbuilder-1.18.3.dist-info/RECORD
