Metadata-Version: 2.4
Name: chemgraphbuilder
Version: 1.18.3
Summary: A package to build chemical knowledge graphs using data from PubChem and Neo4j
Author-email: Asmaa Ali Abdelwahab <asmaa.a.abdelwahab@gmail.com>
License:                     GNU GENERAL PUBLIC LICENSE
Classifier: Programming Language :: Python :: 3
Classifier: License :: OSI Approved :: GNU General Public License v3 (GPLv3)
Classifier: Operating System :: OS Independent
Requires-Python: >=3.8
Requires-Dist: beautifulsoup4
Requires-Dist: matplotlib
Requires-Dist: numpy
Requires-Dist: pandas
Requires-Dist: neo4j
Requires-Dist: requests
Requires-Dist: xmltodict
Requires-Dist: dask
